odoo/addons/company_default_partner_pricelist/README.rst
odoo/addons/company_default_partner_pricelist/__init__.py
odoo/addons/company_default_partner_pricelist/__manifest__.py
odoo/addons/company_default_partner_pricelist/i18n/company_default_partner_pricelist.pot
odoo/addons/company_default_partner_pricelist/migrations/13.0.1.0.1/post-migration.py
odoo/addons/company_default_partner_pricelist/models/__init__.py
odoo/addons/company_default_partner_pricelist/models/res_company.py
odoo/addons/company_default_partner_pricelist/readme/CONTRIBUTORS.rst
odoo/addons/company_default_partner_pricelist/readme/DESCRIPTION.rst
odoo/addons/company_default_partner_pricelist/readme/USAGE.rst
odoo/addons/company_default_partner_pricelist/static/description/icon.png
odoo/addons/company_default_partner_pricelist/static/description/index.html
odoo/addons/company_default_partner_pricelist/tests/__init__.py
odoo/addons/company_default_partner_pricelist/tests/test_company_default_partner_pricelist.py
odoo/addons/company_default_partner_pricelist/views/res_company_views.xml
odoo13_addon_company_default_partner_pricelist-13.0.1.0.2.dev2.dist-info/METADATA
odoo13_addon_company_default_partner_pricelist-13.0.1.0.2.dev2.dist-info/WHEEL
odoo13_addon_company_default_partner_pricelist-13.0.1.0.2.dev2.dist-info/top_level.txt
odoo13_addon_company_default_partner_pricelist-13.0.1.0.2.dev2.dist-info/RECORD
